{
  "name": "Generic Form Submissions",
  "active": true,
  "settings": {
    "executionOrder": "v1"
  },
  "tags": [],
  "nodes": [
    {
      "parameters": {
        "content": "## Generic Form Submissions Workflow\n\nAccepts POST requests at `/webhook/forms` with payload:\n```json\n{ \"form_type\": \"some-form\", \"data\": { ... } }\n```\n\nInserts into the `form_submissions` table with JSONB data column.\n\n### Email Notifications\nAfter insert, routes by `form_type` to send:\n- **Admin notification** to daniel.snell@ (cc: courtney.gwynn@)\n- **User confirmation** to the submitter's email\n\nSupported forms: `texas-tech-compute`, `watts-for-workers`\n\n### Editing Emails\nEdit the `.mjml` source files in `emails/`, then run:\n```\ncd emails && for f in *.mjml; do [[ \"$f\" == _* ]] && continue; mjml \"$f\" -o \"${f%.mjml}.html\" --config.minify true; done\n```\nThen run `node build-workflow.js` to regenerate this workflow JSON."
      },
      "id": "00000000-0000-0000-0000-000000000001",
      "name": "Notes",
      "type": "n8n-nodes-base.stickyNote",
      "typeVersion": 1,
      "position": [
        -192,
        640
      ]
    },
    {
      "parameters": {
        "httpMethod": "POST",
        "path": "forms",
        "responseMode": "responseNode",
        "options": {
          "responseHeaders": {
            "entries": [
              {
                "name": "Access-Control-Allow-Origin",
                "value": "*"
              }
            ]
          }
        }
      },
      "id": "a1b2c3d4-0001-0001-0001-000000000001",
      "name": "Webhook",
      "type": "n8n-nodes-base.webhook",
      "typeVersion": 1.1,
      "position": [
        -192,
        1040
      ],
      "webhookId": "forms"
    },
    {
      "parameters": {
        "jsCode": "const body = $input.first().json.body;\n\nif (!body.form_type || typeof body.form_type !== 'string' || body.form_type.trim() === '') {\n  return [{ json: { valid: false, message: 'Missing or invalid form_type' } }];\n}\n\nif (!body.data || typeof body.data !== 'object' || Array.isArray(body.data)) {\n  return [{ json: { valid: false, message: 'Missing or invalid data object' } }];\n}\n\nreturn [{ json: { valid: true, form_type: body.form_type.trim(), data: body.data } }];"
      },
      "id": "a1b2c3d4-0001-0001-0001-000000000002",
      "name": "Validate Input",
      "type": "n8n-nodes-base.code",
      "typeVersion": 2,
      "position": [
        28,
        1040
      ]
    },
    {
      "parameters": {
        "rules": {
          "values": [
            {
              "conditions": {
                "options": {
                  "caseSensitive": false,
                  "leftValue": "",
                  "typeValidation": "loose"
                },
                "conditions": [
                  {
                    "leftValue": "={{ $json.valid }}",
                    "rightValue": true,
                    "operator": {
                      "type": "boolean",
                      "operation": "equals"
                    }
                  }
                ],
                "combinator": "and"
              },
              "renameOutput": true,
              "outputKey": "valid"
            },
            {
              "conditions": {
                "options": {
                  "caseSensitive": false,
                  "leftValue": "",
                  "typeValidation": "loose"
                },
                "conditions": [
                  {
                    "leftValue": "={{ $json.valid }}",
                    "rightValue": false,
                    "operator": {
                      "type": "boolean",
                      "operation": "equals"
                    }
                  }
                ],
                "combinator": "and"
              },
              "renameOutput": true,
              "outputKey": "invalid"
            }
          ]
        },
        "options": {}
      },
      "id": "a1b2c3d4-0001-0001-0001-000000000003",
      "name": "Route",
      "type": "n8n-nodes-base.switch",
      "typeVersion": 3,
      "position": [
        248,
        1040
      ]
    },
    {
      "parameters": {
        "operation": "executeQuery",
        "query": "INSERT INTO form_submissions (form_type, data) VALUES ($1, $2::jsonb) RETURNING id, form_type, created_at",
        "options": {
          "queryReplacement": "={{ $json.form_type }},={{ JSON.stringify($json.data) }}"
        }
      },
      "id": "a1b2c3d4-0001-0001-0001-000000000004",
      "name": "Insert Submission",
      "type": "n8n-nodes-base.postgres",
      "typeVersion": 2.5,
      "position": [
        468,
        940
      ],
      "credentials": {
        "postgres": {
          "id": "qYLP1qqStnwaPbh4",
          "name": "TWG | PG"
        }
      }
    },
    {
      "parameters": {
        "respondWith": "json",
        "responseBody": "={{ JSON.stringify({ success: true, id: $json.id }) }}",
        "options": {
          "responseCode": 200,
          "responseHeaders": {
            "entries": [
              {
                "name": "Access-Control-Allow-Origin",
                "value": "*"
              }
            ]
          }
        }
      },
      "id": "a1b2c3d4-0001-0001-0001-000000000005",
      "name": "Success Response",
      "type": "n8n-nodes-base.respondToWebhook",
      "typeVersion": 1.1,
      "position": [
        688,
        940
      ]
    },
    {
      "parameters": {
        "respondWith": "json",
        "responseBody": "={{ JSON.stringify({ success: false, message: $json.message || 'Validation failed' }) }}",
        "options": {
          "responseCode": 400,
          "responseHeaders": {
            "entries": [
              {
                "name": "Access-Control-Allow-Origin",
                "value": "*"
              }
            ]
          }
        }
      },
      "id": "a1b2c3d4-0001-0001-0001-000000000006",
      "name": "Error Response",
      "type": "n8n-nodes-base.respondToWebhook",
      "typeVersion": 1.1,
      "position": [
        468,
        1140
      ]
    },
    {
      "parameters": {
        "rules": {
          "values": [
            {
              "conditions": {
                "options": {
                  "caseSensitive": false,
                  "leftValue": "",
                  "typeValidation": "loose"
                },
                "conditions": [
                  {
                    "leftValue": "={{ $('Validate Input').item.json.form_type }}",
                    "rightValue": "texas-tech-compute",
                    "operator": {
                      "type": "string",
                      "operation": "equals"
                    }
                  }
                ],
                "combinator": "and"
              },
              "renameOutput": true,
              "outputKey": "texas-tech-compute"
            },
            {
              "conditions": {
                "options": {
                  "caseSensitive": false,
                  "leftValue": "",
                  "typeValidation": "loose"
                },
                "conditions": [
                  {
                    "leftValue": "={{ $('Validate Input').item.json.form_type }}",
                    "rightValue": "watts-for-workers",
                    "operator": {
                      "type": "string",
                      "operation": "equals"
                    }
                  }
                ],
                "combinator": "and"
              },
              "renameOutput": true,
              "outputKey": "watts-for-workers"
            }
          ]
        },
        "options": {}
      },
      "id": "a1b2c3d4-0001-0001-0001-000000000010",
      "name": "Switch on Form Type",
      "type": "n8n-nodes-base.switch",
      "typeVersion": 3,
      "position": [
        688,
        1140
      ]
    },
    {
      "parameters": {
        "fromEmail": "notifications@m.thiswayglobal.com",
        "toEmail": "daniel.snell@thiswayglobal.com",
        "ccEmail": "courtney.gwynn@thiswayglobal.com",
        "subject": "=New Compute Inquiry: {{ $('Validate Input').item.json.data.first_name }} {{ $('Validate Input').item.json.data.last_name }}",
        "html": "=<!doctype html><html lang=\"und\" dir=\"auto\" xmlns=\"http://www.w3.org/1999/xhtml\" xmlns:v=\"urn:schemas-microsoft-com:vml\" xmlns:o=\"urn:schemas-microsoft-com:office:office\"><head><title></title><!--[if !mso]><!--><meta http-equiv=\"X-UA-Compatible\" content=\"IE=edge\"><!--<![endif]--><meta http-equiv=\"Content-Type\" content=\"text/html; charset=UTF-8\"><meta name=\"viewport\" content=\"width=device-width,initial-scale=1\"><style type=\"text/css\">#outlook a {      padding: 0;    }    body {      margin: 0;      padding: 0;      -webkit-text-size-adjust: 100%;      -ms-text-size-adjust: 100%;    }    table,    td {      border-collapse: collapse;      mso-table-lspace: 0pt;      mso-table-rspace: 0pt;    }    img {      border: 0;      height: auto;      line-height: 100%;      outline: none;      text-decoration: none;      -ms-interpolation-mode: bicubic;    }    p {      display: block;      margin: 13px 0;    }</style><!--[if mso]>    <noscript>    <xml>    <o:OfficeDocumentSettings>      <o:AllowPNG/>      <o:PixelsPerInch>96</o:PixelsPerInch>    </o:OfficeDocumentSettings>    </xml>    </noscript>    <![endif]--><!--[if lte mso 11]>    <style type=\"text/css\">      .mj-outlook-group-fix { width:100% !important; }    </style>    <![endif]--><!--[if !mso]><!--><link href=\"https://fonts.googleapis.com/css?family=Roboto:300,400,500,700\" rel=\"stylesheet\" type=\"text/css\"><style type=\"text/css\">@import url(https://fonts.googleapis.com/css?family=Roboto:300,400,500,700);</style><!--<![endif]--><style type=\"text/css\">@media only screen and (min-width:480px) {      .mj-column-per-100 {        width: 100% !important;        max-width: 100%;      }    }</style><style media=\"screen and (min-width:480px)\">.moz-text-html .mj-column-per-100 {      width: 100% !important;      max-width: 100%;    }</style><style type=\"text/css\">@media only screen and (max-width:479px) {      table.mj-full-width-mobile {        width: 100% !important;      }      td.mj-full-width-mobile {        width: auto !important;      }    }</style></head><body style=\"word-spacing:normal;background-color:#f4f4f5;\"><div aria-roledescription=\"email\" style=\"background-color:#f4f4f5;\" role=\"article\" lang=\"und\" dir=\"auto\"><!--[if mso | IE]><table align=\"center\" border=\"0\" cellpadding=\"0\" cellspacing=\"0\" class=\"\" role=\"presentation\" style=\"width:600px;\" width=\"600\" ><tr><td style=\"line-height:0px;font-size:0px;mso-line-height-rule:exactly;\"><![endif]--><div style=\"margin:0px auto;max-width:600px;\"><table align=\"center\" border=\"0\" cellpadding=\"0\" cellspacing=\"0\" role=\"presentation\" style=\"width:100%;\"><tbody><tr><td style=\"direction:ltr;font-size:0px;padding:32px 16px 0;text-align:center;\"><!--[if mso | IE]><table role=\"presentation\" border=\"0\" cellpadding=\"0\" cellspacing=\"0\"><tr><td class=\"\" style=\"vertical-align:top;width:568px;\" ><![endif]--><div class=\"mj-column-per-100 mj-outlook-group-fix\" style=\"font-size:0px;text-align:left;direction:ltr;display:inline-block;vertical-align:top;width:100%;\"><table border=\"0\" cellpadding=\"0\" cellspacing=\"0\" role=\"presentation\" style=\"vertical-align:top;\" width=\"100%\"><tbody><tr><td align=\"center\" style=\"font-size:0px;padding:10px 25px;padding-bottom:24px;word-break:break-word;\"><table border=\"0\" cellpadding=\"0\" cellspacing=\"0\" role=\"presentation\" style=\"border-collapse:collapse;border-spacing:0px;\"><tbody><tr><td style=\"width:140px;\"><img alt=\"ThisWay Global\" src=\"https://thiswayglobal.com/images/logo.png\" style=\"border:0;display:block;outline:none;text-decoration:none;height:auto;width:100%;font-size:13px;\" width=\"140\" height=\"auto\"></td></tr></tbody></table></td></tr></tbody></table></div><!--[if mso | IE]></td></tr></table><![endif]--></td></tr></tbody></table></div><!--[if mso | IE]></td></tr></table><table align=\"center\" border=\"0\" cellpadding=\"0\" cellspacing=\"0\" class=\"\" role=\"presentation\" style=\"width:600px;\" width=\"600\" bgcolor=\"#f4f4f5\" ><tr><td style=\"line-height:0px;font-size:0px;mso-line-height-rule:exactly;\"><![endif]--><div style=\"background:#f4f4f5;background-color:#f4f4f5;margin:0px auto;max-width:600px;\"><table align=\"center\" border=\"0\" cellpadding=\"0\" cellspacing=\"0\" role=\"presentation\" style=\"background:#f4f4f5;background-color:#f4f4f5;width:100%;\"><tbody><tr><td style=\"direction:ltr;font-size:0px;padding:0 16px 32px;text-align:center;\"><!--[if mso | IE]><table role=\"presentation\" border=\"0\" cellpadding=\"0\" cellspacing=\"0\"><tr><td class=\"\" width=\"600px\" ><table align=\"center\" border=\"0\" cellpadding=\"0\" cellspacing=\"0\" class=\"\" role=\"presentation\" style=\"width:568px;\" width=\"568\" bgcolor=\"#ffffff\" ><tr><td style=\"line-height:0px;font-size:0px;mso-line-height-rule:exactly;\"><![endif]--><div style=\"background:#ffffff;background-color:#ffffff;margin:0px auto;max-width:568px;border-radius:12px;overflow:hidden;\"><table align=\"center\" border=\"0\" cellpadding=\"0\" cellspacing=\"0\" role=\"presentation\" style=\"background:#ffffff;background-color:#ffffff;width:100%;border-collapse:separate;\"><tbody><tr><td style=\"border-radius:12px;direction:ltr;font-size:0px;padding:40px 32px 32px;text-align:center;\"><!--[if mso | IE]><table role=\"presentation\" border=\"0\" cellpadding=\"0\" cellspacing=\"0\"><tr><td class=\"\" style=\"vertical-align:top;width:504px;\" ><![endif]--><div class=\"mj-column-per-100 mj-outlook-group-fix\" style=\"font-size:0px;text-align:left;direction:ltr;display:inline-block;vertical-align:top;width:100%;\"><table border=\"0\" cellpadding=\"0\" cellspacing=\"0\" role=\"presentation\" style=\"vertical-align:top;\" width=\"100%\"><tbody><tr><td align=\"left\" style=\"font-size:0px;padding:10px 25px;padding-bottom:4px;word-break:break-word;\"><div style=\"font-family:system-ui, -apple-system, BlinkMacSystemFont, 'Segoe UI', Roboto, sans-serif;font-size:22px;font-weight:700;line-height:1.6;text-align:left;color:#18181b;\">New Compute Inquiry</div></td></tr><tr><td align=\"left\" style=\"font-size:0px;padding:10px 25px;padding-bottom:24px;word-break:break-word;\"><div style=\"font-family:system-ui, -apple-system, BlinkMacSystemFont, 'Segoe UI', Roboto, sans-serif;font-size:14px;line-height:1.6;text-align:left;color:#71717a;\">A new inquiry has been submitted for Texas Tech computing power.</div></td></tr><tr><td align=\"center\" style=\"font-size:0px;padding:0 0 24px;word-break:break-word;\"><p style=\"border-top:solid 1px #e4e4e7;font-size:1px;margin:0px auto;width:100%;\"></p><!--[if mso | IE]><table align=\"center\" border=\"0\" cellpadding=\"0\" cellspacing=\"0\" style=\"border-top:solid 1px #e4e4e7;font-size:1px;margin:0px auto;width:504px;\" role=\"presentation\" width=\"504px\" ><tr><td style=\"height:0;line-height:0;\"> &nbsp;</td></tr></table><![endif]--></td></tr></tbody></table></div><!--[if mso | IE]></td></tr></table><![endif]--></td></tr></tbody></table></div><!--[if mso | IE]></td></tr></table></td></tr><tr><td class=\"\" width=\"600px\" ><table align=\"center\" border=\"0\" cellpadding=\"0\" cellspacing=\"0\" class=\"\" role=\"presentation\" style=\"width:568px;\" width=\"568\" bgcolor=\"#ffffff\" ><tr><td style=\"line-height:0px;font-size:0px;mso-line-height-rule:exactly;\"><![endif]--><div style=\"background:#ffffff;background-color:#ffffff;margin:0px auto;max-width:568px;border-radius:12px;overflow:hidden;\"><table align=\"center\" border=\"0\" cellpadding=\"0\" cellspacing=\"0\" role=\"presentation\" style=\"background:#ffffff;background-color:#ffffff;width:100%;border-collapse:separate;\"><tbody><tr><td style=\"border-radius:12px;direction:ltr;font-size:0px;padding:0 32px 8px;text-align:center;\"><!--[if mso | IE]><table role=\"presentation\" border=\"0\" cellpadding=\"0\" cellspacing=\"0\"><tr><td class=\"\" style=\"vertical-align:top;width:504px;\" ><![endif]--><div class=\"mj-column-per-100 mj-outlook-group-fix\" style=\"font-size:0px;text-align:left;direction:ltr;display:inline-block;vertical-align:top;width:100%;\"><table border=\"0\" cellpadding=\"0\" cellspacing=\"0\" role=\"presentation\" width=\"100%\" style=\"border-collapse:separate;\"><tbody><tr><td style=\"background-color:#f4f4f5;border-radius:8px;vertical-align:top;border-collapse:separate;padding:20px;\"><table border=\"0\" cellpadding=\"0\" cellspacing=\"0\" role=\"presentation\" width=\"100%\"><tbody><tr><td align=\"left\" style=\"font-size:0px;padding:0 0 4px;word-break:break-word;\"><div style=\"font-family:system-ui, -apple-system, BlinkMacSystemFont, 'Segoe UI', Roboto, sans-serif;font-size:11px;line-height:1.6;text-align:left;color:#71717a;\">NAME</div></td></tr><tr><td align=\"left\" style=\"font-size:0px;padding:0;word-break:break-word;\"><div style=\"font-family:system-ui, -apple-system, BlinkMacSystemFont, 'Segoe UI', Roboto, sans-serif;font-size:16px;font-weight:600;line-height:1.6;text-align:left;color:#18181b;\">{{ $('Validate Input').item.json.data.first_name }} {{ $('Validate Input').item.json.data.last_name }}</div></td></tr></tbody></table></td></tr></tbody></table></div><!--[if mso | IE]></td></tr></table><![endif]--></td></tr></tbody></table></div><!--[if mso | IE]></td></tr></table></td></tr><tr><td class=\"\" width=\"600px\" ><table align=\"center\" border=\"0\" cellpadding=\"0\" cellspacing=\"0\" class=\"\" role=\"presentation\" style=\"width:568px;\" width=\"568\" bgcolor=\"#ffffff\" ><tr><td style=\"line-height:0px;font-size:0px;mso-line-height-rule:exactly;\"><![endif]--><div style=\"background:#ffffff;background-color:#ffffff;margin:0px auto;max-width:568px;border-radius:12px;overflow:hidden;\"><table align=\"center\" border=\"0\" cellpadding=\"0\" cellspacing=\"0\" role=\"presentation\" style=\"background:#ffffff;background-color:#ffffff;width:100%;border-collapse:separate;\"><tbody><tr><td style=\"border-radius:12px;direction:ltr;font-size:0px;padding:0 32px 8px;text-align:center;\"><!--[if mso | IE]><table role=\"presentation\" border=\"0\" cellpadding=\"0\" cellspacing=\"0\"><tr><td class=\"\" style=\"vertical-align:top;width:504px;\" ><![endif]--><div class=\"mj-column-per-100 mj-outlook-group-fix\" style=\"font-size:0px;text-align:left;direction:ltr;display:inline-block;vertical-align:top;width:100%;\"><table border=\"0\" cellpadding=\"0\" cellspacing=\"0\" role=\"presentation\" width=\"100%\" style=\"border-collapse:separate;\"><tbody><tr><td style=\"background-color:#f4f4f5;border-radius:8px;vertical-align:top;border-collapse:separate;padding:20px;\"><table border=\"0\" cellpadding=\"0\" cellspacing=\"0\" role=\"presentation\" width=\"100%\"><tbody><tr><td align=\"left\" style=\"font-size:0px;padding:0 0 4px;word-break:break-word;\"><div style=\"font-family:system-ui, -apple-system, BlinkMacSystemFont, 'Segoe UI', Roboto, sans-serif;font-size:11px;line-height:1.6;text-align:left;color:#71717a;\">EMAIL</div></td></tr><tr><td align=\"left\" style=\"font-size:0px;padding:0;word-break:break-word;\"><div style=\"font-family:system-ui, -apple-system, BlinkMacSystemFont, 'Segoe UI', Roboto, sans-serif;font-size:16px;font-weight:600;line-height:1.6;text-align:left;color:#18181b;\">{{ $('Validate Input').item.json.data.email }}</div></td></tr></tbody></table></td></tr></tbody></table></div><!--[if mso | IE]></td></tr></table><![endif]--></td></tr></tbody></table></div><!--[if mso | IE]></td></tr></table></td></tr><tr><td class=\"\" width=\"600px\" ><table align=\"center\" border=\"0\" cellpadding=\"0\" cellspacing=\"0\" class=\"\" role=\"presentation\" style=\"width:568px;\" width=\"568\" bgcolor=\"#ffffff\" ><tr><td style=\"line-height:0px;font-size:0px;mso-line-height-rule:exactly;\"><![endif]--><div style=\"background:#ffffff;background-color:#ffffff;margin:0px auto;max-width:568px;border-radius:12px;overflow:hidden;\"><table align=\"center\" border=\"0\" cellpadding=\"0\" cellspacing=\"0\" role=\"presentation\" style=\"background:#ffffff;background-color:#ffffff;width:100%;border-collapse:separate;\"><tbody><tr><td style=\"border-radius:12px;direction:ltr;font-size:0px;padding:0 32px 8px;text-align:center;\"><!--[if mso | IE]><table role=\"presentation\" border=\"0\" cellpadding=\"0\" cellspacing=\"0\"><tr><td class=\"\" style=\"vertical-align:top;width:504px;\" ><![endif]--><div class=\"mj-column-per-100 mj-outlook-group-fix\" style=\"font-size:0px;text-align:left;direction:ltr;display:inline-block;vertical-align:top;width:100%;\"><table border=\"0\" cellpadding=\"0\" cellspacing=\"0\" role=\"presentation\" width=\"100%\" style=\"border-collapse:separate;\"><tbody><tr><td style=\"background-color:#f4f4f5;border-radius:8px;vertical-align:top;border-collapse:separate;padding:20px;\"><table border=\"0\" cellpadding=\"0\" cellspacing=\"0\" role=\"presentation\" width=\"100%\"><tbody><tr><td align=\"left\" style=\"font-size:0px;padding:0 0 4px;word-break:break-word;\"><div style=\"font-family:system-ui, -apple-system, BlinkMacSystemFont, 'Segoe UI', Roboto, sans-serif;font-size:11px;line-height:1.6;text-align:left;color:#71717a;\">COMPANY</div></td></tr><tr><td align=\"left\" style=\"font-size:0px;padding:0;word-break:break-word;\"><div style=\"font-family:system-ui, -apple-system, BlinkMacSystemFont, 'Segoe UI', Roboto, sans-serif;font-size:16px;font-weight:600;line-height:1.6;text-align:left;color:#18181b;\">{{ $('Validate Input').item.json.data.company }}</div></td></tr></tbody></table></td></tr></tbody></table></div><!--[if mso | IE]></td></tr></table><![endif]--></td></tr></tbody></table></div><!--[if mso | IE]></td></tr></table></td></tr><tr><td class=\"\" width=\"600px\" ><table align=\"center\" border=\"0\" cellpadding=\"0\" cellspacing=\"0\" class=\"\" role=\"presentation\" style=\"width:568px;\" width=\"568\" bgcolor=\"#ffffff\" ><tr><td style=\"line-height:0px;font-size:0px;mso-line-height-rule:exactly;\"><![endif]--><div style=\"background:#ffffff;background-color:#ffffff;margin:0px auto;max-width:568px;border-radius:12px;overflow:hidden;\"><table align=\"center\" border=\"0\" cellpadding=\"0\" cellspacing=\"0\" role=\"presentation\" style=\"background:#ffffff;background-color:#ffffff;width:100%;border-collapse:separate;\"><tbody><tr><td style=\"border-radius:12px;direction:ltr;font-size:0px;padding:0 32px 8px;text-align:center;\"><!--[if mso | IE]><table role=\"presentation\" border=\"0\" cellpadding=\"0\" cellspacing=\"0\"><tr><td class=\"\" style=\"vertical-align:top;width:504px;\" ><![endif]--><div class=\"mj-column-per-100 mj-outlook-group-fix\" style=\"font-size:0px;text-align:left;direction:ltr;display:inline-block;vertical-align:top;width:100%;\"><table border=\"0\" cellpadding=\"0\" cellspacing=\"0\" role=\"presentation\" width=\"100%\" style=\"border-collapse:separate;\"><tbody><tr><td style=\"background-color:#f4f4f5;border-radius:8px;vertical-align:top;border-collapse:separate;padding:20px;\"><table border=\"0\" cellpadding=\"0\" cellspacing=\"0\" role=\"presentation\" width=\"100%\"><tbody><tr><td align=\"left\" style=\"font-size:0px;padding:0 0 4px;word-break:break-word;\"><div style=\"font-family:system-ui, -apple-system, BlinkMacSystemFont, 'Segoe UI', Roboto, sans-serif;font-size:11px;line-height:1.6;text-align:left;color:#71717a;\">TITLE / POSITION</div></td></tr><tr><td align=\"left\" style=\"font-size:0px;padding:0;word-break:break-word;\"><div style=\"font-family:system-ui, -apple-system, BlinkMacSystemFont, 'Segoe UI', Roboto, sans-serif;font-size:16px;font-weight:600;line-height:1.6;text-align:left;color:#18181b;\">{{ $('Validate Input').item.json.data.title }}</div></td></tr></tbody></table></td></tr></tbody></table></div><!--[if mso | IE]></td></tr></table><![endif]--></td></tr></tbody></table></div><!--[if mso | IE]></td></tr></table></td></tr><tr><td class=\"\" width=\"600px\" ><table align=\"center\" border=\"0\" cellpadding=\"0\" cellspacing=\"0\" class=\"\" role=\"presentation\" style=\"width:568px;\" width=\"568\" bgcolor=\"#ffffff\" ><tr><td style=\"line-height:0px;font-size:0px;mso-line-height-rule:exactly;\"><![endif]--><div style=\"background:#ffffff;background-color:#ffffff;margin:0px auto;max-width:568px;border-radius:12px;overflow:hidden;\"><table align=\"center\" border=\"0\" cellpadding=\"0\" cellspacing=\"0\" role=\"presentation\" style=\"background:#ffffff;background-color:#ffffff;width:100%;border-collapse:separate;\"><tbody><tr><td style=\"border-radius:12px;direction:ltr;font-size:0px;padding:0 32px 8px;text-align:center;\"><!--[if mso | IE]><table role=\"presentation\" border=\"0\" cellpadding=\"0\" cellspacing=\"0\"><tr><td class=\"\" style=\"vertical-align:top;width:504px;\" ><![endif]--><div class=\"mj-column-per-100 mj-outlook-group-fix\" style=\"font-size:0px;text-align:left;direction:ltr;display:inline-block;vertical-align:top;width:100%;\"><table border=\"0\" cellpadding=\"0\" cellspacing=\"0\" role=\"presentation\" width=\"100%\" style=\"border-collapse:separate;\"><tbody><tr><td style=\"background-color:#f4f4f5;border-radius:8px;vertical-align:top;border-collapse:separate;padding:20px;\"><table border=\"0\" cellpadding=\"0\" cellspacing=\"0\" role=\"presentation\" width=\"100%\"><tbody><tr><td align=\"left\" style=\"font-size:0px;padding:0 0 4px;word-break:break-word;\"><div style=\"font-family:system-ui, -apple-system, BlinkMacSystemFont, 'Segoe UI', Roboto, sans-serif;font-size:11px;line-height:1.6;text-align:left;color:#71717a;\">TIMELINE</div></td></tr><tr><td align=\"left\" style=\"font-size:0px;padding:0;word-break:break-word;\"><div style=\"font-family:system-ui, -apple-system, BlinkMacSystemFont, 'Segoe UI', Roboto, sans-serif;font-size:16px;font-weight:600;line-height:1.6;text-align:left;color:#18181b;\">{{ $('Validate Input').item.json.data.urgency }}</div></td></tr></tbody></table></td></tr></tbody></table></div><!--[if mso | IE]></td></tr></table><![endif]--></td></tr></tbody></table></div><!--[if mso | IE]></td></tr></table></td></tr><tr><td class=\"\" width=\"600px\" ><table align=\"center\" border=\"0\" cellpadding=\"0\" cellspacing=\"0\" class=\"\" role=\"presentation\" style=\"width:568px;\" width=\"568\" bgcolor=\"#ffffff\" ><tr><td style=\"line-height:0px;font-size:0px;mso-line-height-rule:exactly;\"><![endif]--><div style=\"background:#ffffff;background-color:#ffffff;margin:0px auto;max-width:568px;border-radius:12px;overflow:hidden;\"><table align=\"center\" border=\"0\" cellpadding=\"0\" cellspacing=\"0\" role=\"presentation\" style=\"background:#ffffff;background-color:#ffffff;width:100%;border-collapse:separate;\"><tbody><tr><td style=\"border-radius:12px;direction:ltr;font-size:0px;padding:0 32px 32px;text-align:center;\"><!--[if mso | IE]><table role=\"presentation\" border=\"0\" cellpadding=\"0\" cellspacing=\"0\"><tr><td class=\"\" style=\"vertical-align:top;width:504px;\" ><![endif]--><div class=\"mj-column-per-100 mj-outlook-group-fix\" style=\"font-size:0px;text-align:left;direction:ltr;display:inline-block;vertical-align:top;width:100%;\"><table border=\"0\" cellpadding=\"0\" cellspacing=\"0\" role=\"presentation\" width=\"100%\" style=\"border-collapse:separate;\"><tbody><tr><td style=\"background-color:#f4f4f5;border-radius:8px;vertical-align:top;border-collapse:separate;padding:20px;\"><table border=\"0\" cellpadding=\"0\" cellspacing=\"0\" role=\"presentation\" width=\"100%\"><tbody><tr><td align=\"left\" style=\"font-size:0px;padding:0 0 4px;word-break:break-word;\"><div style=\"font-family:system-ui, -apple-system, BlinkMacSystemFont, 'Segoe UI', Roboto, sans-serif;font-size:11px;line-height:1.6;text-align:left;color:#71717a;\">ADDITIONAL NOTES</div></td></tr><tr><td align=\"left\" style=\"font-size:0px;padding:0;word-break:break-word;\"><div style=\"font-family:system-ui, -apple-system, BlinkMacSystemFont, 'Segoe UI', Roboto, sans-serif;font-size:16px;font-weight:600;line-height:1.6;text-align:left;color:#18181b;\">{{ $('Validate Input').item.json.data.note }}</div></td></tr></tbody></table></td></tr></tbody></table></div><!--[if mso | IE]></td></tr></table><![endif]--></td></tr></tbody></table></div><!--[if mso | IE]></td></tr></table></td></tr><tr><td class=\"\" width=\"600px\" ><table align=\"center\" border=\"0\" cellpadding=\"0\" cellspacing=\"0\" class=\"\" role=\"presentation\" style=\"width:568px;\" width=\"568\" ><tr><td style=\"line-height:0px;font-size:0px;mso-line-height-rule:exactly;\"><![endif]--><div style=\"margin:0px auto;max-width:568px;\"><table align=\"center\" border=\"0\" cellpadding=\"0\" cellspacing=\"0\" role=\"presentation\" style=\"width:100%;\"><tbody><tr><td style=\"direction:ltr;font-size:0px;padding:24px 32px 0;text-align:center;\"><!--[if mso | IE]><table role=\"presentation\" border=\"0\" cellpadding=\"0\" cellspacing=\"0\"><tr><td class=\"\" style=\"vertical-align:top;width:504px;\" ><![endif]--><div class=\"mj-column-per-100 mj-outlook-group-fix\" style=\"font-size:0px;text-align:left;direction:ltr;display:inline-block;vertical-align:top;width:100%;\"><table border=\"0\" cellpadding=\"0\" cellspacing=\"0\" role=\"presentation\" style=\"vertical-align:top;\" width=\"100%\"><tbody><tr><td align=\"center\" style=\"font-size:0px;padding:10px 25px;word-break:break-word;\"><div style=\"font-family:system-ui, -apple-system, BlinkMacSystemFont, 'Segoe UI', Roboto, sans-serif;font-size:12px;line-height:1.6;text-align:center;color:#a1a1aa;\">ThisWay Global &middot; Austin, TX</div></td></tr></tbody></table></div><!--[if mso | IE]></td></tr></table><![endif]--></td></tr></tbody></table></div><!--[if mso | IE]></td></tr></table></td></tr></table><![endif]--></td></tr></tbody></table></div><!--[if mso | IE]></td></tr></table><![endif]--></div></body></html>"
      },
      "type": "n8n-nodes-base.mailgun",
      "typeVersion": 1,
      "position": [
        928,
        1040
      ],
      "id": "a1b2c3d4-0001-0001-0001-000000000011",
      "name": "TTC: Notify Admin",
      "credentials": {
        "mailgunApi": {
          "id": "lHQnhWsSULcKXB4f",
          "name": "Amalgamy.ai"
        }
      }
    },
    {
      "parameters": {
        "fromEmail": "notifications@m.thiswayglobal.com",
        "toEmail": "={{ $('Validate Input').item.json.data.email }}",
        "subject": "=Thank You for Your Inquiry",
        "html": "=<!doctype html><html lang=\"und\" dir=\"auto\" xmlns=\"http://www.w3.org/1999/xhtml\" xmlns:v=\"urn:schemas-microsoft-com:vml\" xmlns:o=\"urn:schemas-microsoft-com:office:office\"><head><title></title><!--[if !mso]><!--><meta http-equiv=\"X-UA-Compatible\" content=\"IE=edge\"><!--<![endif]--><meta http-equiv=\"Content-Type\" content=\"text/html; charset=UTF-8\"><meta name=\"viewport\" content=\"width=device-width,initial-scale=1\"><style type=\"text/css\">#outlook a {      padding: 0;    }    body {      margin: 0;      padding: 0;      -webkit-text-size-adjust: 100%;      -ms-text-size-adjust: 100%;    }    table,    td {      border-collapse: collapse;      mso-table-lspace: 0pt;      mso-table-rspace: 0pt;    }    img {      border: 0;      height: auto;      line-height: 100%;      outline: none;      text-decoration: none;      -ms-interpolation-mode: bicubic;    }    p {      display: block;      margin: 13px 0;    }</style><!--[if mso]>    <noscript>    <xml>    <o:OfficeDocumentSettings>      <o:AllowPNG/>      <o:PixelsPerInch>96</o:PixelsPerInch>    </o:OfficeDocumentSettings>    </xml>    </noscript>    <![endif]--><!--[if lte mso 11]>    <style type=\"text/css\">      .mj-outlook-group-fix { width:100% !important; }    </style>    <![endif]--><!--[if !mso]><!--><link href=\"https://fonts.googleapis.com/css?family=Roboto:300,400,500,700\" rel=\"stylesheet\" type=\"text/css\"><style type=\"text/css\">@import url(https://fonts.googleapis.com/css?family=Roboto:300,400,500,700);</style><!--<![endif]--><style type=\"text/css\">@media only screen and (min-width:480px) {      .mj-column-per-100 {        width: 100% !important;        max-width: 100%;      }    }</style><style media=\"screen and (min-width:480px)\">.moz-text-html .mj-column-per-100 {      width: 100% !important;      max-width: 100%;    }</style><style type=\"text/css\">@media only screen and (max-width:479px) {      table.mj-full-width-mobile {        width: 100% !important;      }      td.mj-full-width-mobile {        width: auto !important;      }    }</style></head><body style=\"word-spacing:normal;background-color:#f4f4f5;\"><div aria-roledescription=\"email\" style=\"background-color:#f4f4f5;\" role=\"article\" lang=\"und\" dir=\"auto\"><!--[if mso | IE]><table align=\"center\" border=\"0\" cellpadding=\"0\" cellspacing=\"0\" class=\"\" role=\"presentation\" style=\"width:600px;\" width=\"600\" ><tr><td style=\"line-height:0px;font-size:0px;mso-line-height-rule:exactly;\"><![endif]--><div style=\"margin:0px auto;max-width:600px;\"><table align=\"center\" border=\"0\" cellpadding=\"0\" cellspacing=\"0\" role=\"presentation\" style=\"width:100%;\"><tbody><tr><td style=\"direction:ltr;font-size:0px;padding:32px 16px 0;text-align:center;\"><!--[if mso | IE]><table role=\"presentation\" border=\"0\" cellpadding=\"0\" cellspacing=\"0\"><tr><td class=\"\" style=\"vertical-align:top;width:568px;\" ><![endif]--><div class=\"mj-column-per-100 mj-outlook-group-fix\" style=\"font-size:0px;text-align:left;direction:ltr;display:inline-block;vertical-align:top;width:100%;\"><table border=\"0\" cellpadding=\"0\" cellspacing=\"0\" role=\"presentation\" style=\"vertical-align:top;\" width=\"100%\"><tbody><tr><td align=\"center\" style=\"font-size:0px;padding:10px 25px;padding-bottom:24px;word-break:break-word;\"><table border=\"0\" cellpadding=\"0\" cellspacing=\"0\" role=\"presentation\" style=\"border-collapse:collapse;border-spacing:0px;\"><tbody><tr><td style=\"width:140px;\"><img alt=\"ThisWay Global\" src=\"https://thiswayglobal.com/images/logo.png\" style=\"border:0;display:block;outline:none;text-decoration:none;height:auto;width:100%;font-size:13px;\" width=\"140\" height=\"auto\"></td></tr></tbody></table></td></tr></tbody></table></div><!--[if mso | IE]></td></tr></table><![endif]--></td></tr></tbody></table></div><!--[if mso | IE]></td></tr></table><table align=\"center\" border=\"0\" cellpadding=\"0\" cellspacing=\"0\" class=\"\" role=\"presentation\" style=\"width:600px;\" width=\"600\" bgcolor=\"#f4f4f5\" ><tr><td style=\"line-height:0px;font-size:0px;mso-line-height-rule:exactly;\"><![endif]--><div style=\"background:#f4f4f5;background-color:#f4f4f5;margin:0px auto;max-width:600px;\"><table align=\"center\" border=\"0\" cellpadding=\"0\" cellspacing=\"0\" role=\"presentation\" style=\"background:#f4f4f5;background-color:#f4f4f5;width:100%;\"><tbody><tr><td style=\"direction:ltr;font-size:0px;padding:0 16px 32px;text-align:center;\"><!--[if mso | IE]><table role=\"presentation\" border=\"0\" cellpadding=\"0\" cellspacing=\"0\"><tr><td class=\"\" width=\"600px\" ><table align=\"center\" border=\"0\" cellpadding=\"0\" cellspacing=\"0\" class=\"\" role=\"presentation\" style=\"width:568px;\" width=\"568\" bgcolor=\"#ffffff\" ><tr><td style=\"line-height:0px;font-size:0px;mso-line-height-rule:exactly;\"><![endif]--><div style=\"background:#ffffff;background-color:#ffffff;margin:0px auto;max-width:568px;border-radius:12px;overflow:hidden;\"><table align=\"center\" border=\"0\" cellpadding=\"0\" cellspacing=\"0\" role=\"presentation\" style=\"background:#ffffff;background-color:#ffffff;width:100%;border-collapse:separate;\"><tbody><tr><td style=\"border-radius:12px;direction:ltr;font-size:0px;padding:40px 32px 32px;text-align:center;\"><!--[if mso | IE]><table role=\"presentation\" border=\"0\" cellpadding=\"0\" cellspacing=\"0\"><tr><td class=\"\" style=\"vertical-align:top;width:504px;\" ><![endif]--><div class=\"mj-column-per-100 mj-outlook-group-fix\" style=\"font-size:0px;text-align:left;direction:ltr;display:inline-block;vertical-align:top;width:100%;\"><table border=\"0\" cellpadding=\"0\" cellspacing=\"0\" role=\"presentation\" style=\"vertical-align:top;\" width=\"100%\"><tbody><tr><td align=\"left\" style=\"font-size:0px;padding:10px 25px;padding-bottom:4px;word-break:break-word;\"><div style=\"font-family:system-ui, -apple-system, BlinkMacSystemFont, 'Segoe UI', Roboto, sans-serif;font-size:22px;font-weight:700;line-height:1.6;text-align:left;color:#18181b;\">Inquiry Received</div></td></tr><tr><td align=\"left\" style=\"font-size:0px;padding:10px 25px;padding-bottom:24px;word-break:break-word;\"><div style=\"font-family:system-ui, -apple-system, BlinkMacSystemFont, 'Segoe UI', Roboto, sans-serif;font-size:14px;line-height:1.6;text-align:left;color:#71717a;\">Thank you for your interest in Texas Tech computing power.</div></td></tr><tr><td align=\"center\" style=\"font-size:0px;padding:0 0 24px;word-break:break-word;\"><p style=\"border-top:solid 1px #e4e4e7;font-size:1px;margin:0px auto;width:100%;\"></p><!--[if mso | IE]><table align=\"center\" border=\"0\" cellpadding=\"0\" cellspacing=\"0\" style=\"border-top:solid 1px #e4e4e7;font-size:1px;margin:0px auto;width:504px;\" role=\"presentation\" width=\"504px\" ><tr><td style=\"height:0;line-height:0;\"> &nbsp;</td></tr></table><![endif]--></td></tr><tr><td align=\"left\" style=\"font-size:0px;padding:10px 25px;padding-bottom:16px;word-break:break-word;\"><div style=\"font-family:system-ui, -apple-system, BlinkMacSystemFont, 'Segoe UI', Roboto, sans-serif;font-size:15px;line-height:1.6;text-align:left;color:#18181b;\">Hi {{ $('Validate Input').item.json.data.first_name }},</div></td></tr><tr><td align=\"left\" style=\"font-size:0px;padding:10px 25px;padding-bottom:16px;word-break:break-word;\"><div style=\"font-family:system-ui, -apple-system, BlinkMacSystemFont, 'Segoe UI', Roboto, sans-serif;font-size:15px;line-height:1.6;text-align:left;color:#18181b;\">Thank you for reaching out about Texas Tech computing resources. We've received your inquiry and our team is reviewing the details. Someone from ThisWay Global will be in touch with you shortly to discuss your computing needs.</div></td></tr></tbody></table></div><!--[if mso | IE]></td></tr></table><![endif]--></td></tr></tbody></table></div><!--[if mso | IE]></td></tr></table></td></tr><tr><td class=\"\" width=\"600px\" ><table align=\"center\" border=\"0\" cellpadding=\"0\" cellspacing=\"0\" class=\"\" role=\"presentation\" style=\"width:568px;\" width=\"568\" bgcolor=\"#ffffff\" ><tr><td style=\"line-height:0px;font-size:0px;mso-line-height-rule:exactly;\"><![endif]--><div style=\"background:#ffffff;background-color:#ffffff;margin:0px auto;max-width:568px;border-radius:12px;overflow:hidden;\"><table align=\"center\" border=\"0\" cellpadding=\"0\" cellspacing=\"0\" role=\"presentation\" style=\"background:#ffffff;background-color:#ffffff;width:100%;border-collapse:separate;\"><tbody><tr><td style=\"border-radius:12px;direction:ltr;font-size:0px;padding:0 32px 24px;text-align:center;\"><!--[if mso | IE]><table role=\"presentation\" border=\"0\" cellpadding=\"0\" cellspacing=\"0\"><tr><td class=\"\" style=\"vertical-align:top;width:504px;\" ><![endif]--><div class=\"mj-column-per-100 mj-outlook-group-fix\" style=\"font-size:0px;text-align:left;direction:ltr;display:inline-block;vertical-align:top;width:100%;\"><table border=\"0\" cellpadding=\"0\" cellspacing=\"0\" role=\"presentation\" width=\"100%\" style=\"border-collapse:separate;\"><tbody><tr><td style=\"background-color:#f4f4f5;border-radius:8px;vertical-align:top;border-collapse:separate;padding:20px;\"><table border=\"0\" cellpadding=\"0\" cellspacing=\"0\" role=\"presentation\" width=\"100%\"><tbody><tr><td align=\"left\" style=\"font-size:0px;padding:0 0 4px;word-break:break-word;\"><div style=\"font-family:system-ui, -apple-system, BlinkMacSystemFont, 'Segoe UI', Roboto, sans-serif;font-size:11px;line-height:1.6;text-align:left;color:#71717a;\">COMPANY</div></td></tr><tr><td align=\"left\" style=\"font-size:0px;padding:0 0 16px;word-break:break-word;\"><div style=\"font-family:system-ui, -apple-system, BlinkMacSystemFont, 'Segoe UI', Roboto, sans-serif;font-size:16px;font-weight:600;line-height:1.6;text-align:left;color:#18181b;\">{{ $('Validate Input').item.json.data.company }}</div></td></tr><tr><td align=\"left\" style=\"font-size:0px;padding:0 0 4px;word-break:break-word;\"><div style=\"font-family:system-ui, -apple-system, BlinkMacSystemFont, 'Segoe UI', Roboto, sans-serif;font-size:11px;line-height:1.6;text-align:left;color:#71717a;\">TIMELINE</div></td></tr><tr><td align=\"left\" style=\"font-size:0px;padding:0;word-break:break-word;\"><div style=\"font-family:system-ui, -apple-system, BlinkMacSystemFont, 'Segoe UI', Roboto, sans-serif;font-size:16px;font-weight:600;line-height:1.6;text-align:left;color:#18181b;\">{{ $('Validate Input').item.json.data.urgency }}</div></td></tr></tbody></table></td></tr></tbody></table></div><!--[if mso | IE]></td></tr></table><![endif]--></td></tr></tbody></table></div><!--[if mso | IE]></td></tr></table></td></tr><tr><td class=\"\" width=\"600px\" ><table align=\"center\" border=\"0\" cellpadding=\"0\" cellspacing=\"0\" class=\"\" role=\"presentation\" style=\"width:568px;\" width=\"568\" bgcolor=\"#ffffff\" ><tr><td style=\"line-height:0px;font-size:0px;mso-line-height-rule:exactly;\"><![endif]--><div style=\"background:#ffffff;background-color:#ffffff;margin:0px auto;max-width:568px;border-radius:12px;overflow:hidden;\"><table align=\"center\" border=\"0\" cellpadding=\"0\" cellspacing=\"0\" role=\"presentation\" style=\"background:#ffffff;background-color:#ffffff;width:100%;border-collapse:separate;\"><tbody><tr><td style=\"border-radius:12px;direction:ltr;font-size:0px;padding:0 32px 32px;text-align:center;\"><!--[if mso | IE]><table role=\"presentation\" border=\"0\" cellpadding=\"0\" cellspacing=\"0\"><tr><td class=\"\" style=\"vertical-align:top;width:504px;\" ><![endif]--><div class=\"mj-column-per-100 mj-outlook-group-fix\" style=\"font-size:0px;text-align:left;direction:ltr;display:inline-block;vertical-align:top;width:100%;\"><table border=\"0\" cellpadding=\"0\" cellspacing=\"0\" role=\"presentation\" style=\"vertical-align:top;\" width=\"100%\"><tbody><tr><td align=\"left\" style=\"font-size:0px;padding:10px 25px;padding-top:8px;word-break:break-word;\"><div style=\"font-family:system-ui, -apple-system, BlinkMacSystemFont, 'Segoe UI', Roboto, sans-serif;font-size:15px;line-height:1.6;text-align:left;color:#18181b;\">Best regards,<br><strong>The ThisWay Global Team</strong></div></td></tr></tbody></table></div><!--[if mso | IE]></td></tr></table><![endif]--></td></tr></tbody></table></div><!--[if mso | IE]></td></tr></table></td></tr><tr><td class=\"\" width=\"600px\" ><table align=\"center\" border=\"0\" cellpadding=\"0\" cellspacing=\"0\" class=\"\" role=\"presentation\" style=\"width:568px;\" width=\"568\" ><tr><td style=\"line-height:0px;font-size:0px;mso-line-height-rule:exactly;\"><![endif]--><div style=\"margin:0px auto;max-width:568px;\"><table align=\"center\" border=\"0\" cellpadding=\"0\" cellspacing=\"0\" role=\"presentation\" style=\"width:100%;\"><tbody><tr><td style=\"direction:ltr;font-size:0px;padding:24px 32px 0;text-align:center;\"><!--[if mso | IE]><table role=\"presentation\" border=\"0\" cellpadding=\"0\" cellspacing=\"0\"><tr><td class=\"\" style=\"vertical-align:top;width:504px;\" ><![endif]--><div class=\"mj-column-per-100 mj-outlook-group-fix\" style=\"font-size:0px;text-align:left;direction:ltr;display:inline-block;vertical-align:top;width:100%;\"><table border=\"0\" cellpadding=\"0\" cellspacing=\"0\" role=\"presentation\" style=\"vertical-align:top;\" width=\"100%\"><tbody><tr><td align=\"center\" style=\"font-size:0px;padding:10px 25px;word-break:break-word;\"><div style=\"font-family:system-ui, -apple-system, BlinkMacSystemFont, 'Segoe UI', Roboto, sans-serif;font-size:12px;line-height:1.6;text-align:center;color:#a1a1aa;\">ThisWay Global &middot; Austin, TX</div></td></tr></tbody></table></div><!--[if mso | IE]></td></tr></table><![endif]--></td></tr></tbody></table></div><!--[if mso | IE]></td></tr></table></td></tr></table><![endif]--></td></tr></tbody></table></div><!--[if mso | IE]></td></tr></table><![endif]--></div></body></html>"
      },
      "type": "n8n-nodes-base.mailgun",
      "typeVersion": 1,
      "position": [
        928,
        1140
      ],
      "id": "a1b2c3d4-0001-0001-0001-000000000012",
      "name": "TTC: Confirm User",
      "credentials": {
        "mailgunApi": {
          "id": "lHQnhWsSULcKXB4f",
          "name": "Amalgamy.ai"
        }
      }
    },
    {
      "parameters": {
        "fromEmail": "notifications@m.thiswayglobal.com",
        "toEmail": "daniel.snell@thiswayglobal.com",
        "ccEmail": "courtney.gwynn@thiswayglobal.com",
        "subject": "=New WattsForWorkers Interest: {{ $('Validate Input').item.json.data.first_name }} {{ $('Validate Input').item.json.data.last_name }}",
        "html": "=<!doctype html><html lang=\"und\" dir=\"auto\" xmlns=\"http://www.w3.org/1999/xhtml\" xmlns:v=\"urn:schemas-microsoft-com:vml\" xmlns:o=\"urn:schemas-microsoft-com:office:office\"><head><title></title><!--[if !mso]><!--><meta http-equiv=\"X-UA-Compatible\" content=\"IE=edge\"><!--<![endif]--><meta http-equiv=\"Content-Type\" content=\"text/html; charset=UTF-8\"><meta name=\"viewport\" content=\"width=device-width,initial-scale=1\"><style type=\"text/css\">#outlook a {      padding: 0;    }    body {      margin: 0;      padding: 0;      -webkit-text-size-adjust: 100%;      -ms-text-size-adjust: 100%;    }    table,    td {      border-collapse: collapse;      mso-table-lspace: 0pt;      mso-table-rspace: 0pt;    }    img {      border: 0;      height: auto;      line-height: 100%;      outline: none;      text-decoration: none;      -ms-interpolation-mode: bicubic;    }    p {      display: block;      margin: 13px 0;    }</style><!--[if mso]>    <noscript>    <xml>    <o:OfficeDocumentSettings>      <o:AllowPNG/>      <o:PixelsPerInch>96</o:PixelsPerInch>    </o:OfficeDocumentSettings>    </xml>    </noscript>    <![endif]--><!--[if lte mso 11]>    <style type=\"text/css\">      .mj-outlook-group-fix { width:100% !important; }    </style>    <![endif]--><!--[if !mso]><!--><link href=\"https://fonts.googleapis.com/css?family=Roboto:300,400,500,700\" rel=\"stylesheet\" type=\"text/css\"><style type=\"text/css\">@import url(https://fonts.googleapis.com/css?family=Roboto:300,400,500,700);</style><!--<![endif]--><style type=\"text/css\">@media only screen and (min-width:480px) {      .mj-column-per-100 {        width: 100% !important;        max-width: 100%;      }    }</style><style media=\"screen and (min-width:480px)\">.moz-text-html .mj-column-per-100 {      width: 100% !important;      max-width: 100%;    }</style><style type=\"text/css\">@media only screen and (max-width:479px) {      table.mj-full-width-mobile {        width: 100% !important;      }      td.mj-full-width-mobile {        width: auto !important;      }    }</style></head><body style=\"word-spacing:normal;background-color:#f4f4f5;\"><div aria-roledescription=\"email\" style=\"background-color:#f4f4f5;\" role=\"article\" lang=\"und\" dir=\"auto\"><!--[if mso | IE]><table align=\"center\" border=\"0\" cellpadding=\"0\" cellspacing=\"0\" class=\"\" role=\"presentation\" style=\"width:600px;\" width=\"600\" ><tr><td style=\"line-height:0px;font-size:0px;mso-line-height-rule:exactly;\"><![endif]--><div style=\"margin:0px auto;max-width:600px;\"><table align=\"center\" border=\"0\" cellpadding=\"0\" cellspacing=\"0\" role=\"presentation\" style=\"width:100%;\"><tbody><tr><td style=\"direction:ltr;font-size:0px;padding:32px 16px 0;text-align:center;\"><!--[if mso | IE]><table role=\"presentation\" border=\"0\" cellpadding=\"0\" cellspacing=\"0\"><tr><td class=\"\" style=\"vertical-align:top;width:568px;\" ><![endif]--><div class=\"mj-column-per-100 mj-outlook-group-fix\" style=\"font-size:0px;text-align:left;direction:ltr;display:inline-block;vertical-align:top;width:100%;\"><table border=\"0\" cellpadding=\"0\" cellspacing=\"0\" role=\"presentation\" style=\"vertical-align:top;\" width=\"100%\"><tbody><tr><td align=\"center\" style=\"font-size:0px;padding:10px 25px;padding-bottom:24px;word-break:break-word;\"><table border=\"0\" cellpadding=\"0\" cellspacing=\"0\" role=\"presentation\" style=\"border-collapse:collapse;border-spacing:0px;\"><tbody><tr><td style=\"width:140px;\"><img alt=\"ThisWay Global\" src=\"https://thiswayglobal.com/images/logo.png\" style=\"border:0;display:block;outline:none;text-decoration:none;height:auto;width:100%;font-size:13px;\" width=\"140\" height=\"auto\"></td></tr></tbody></table></td></tr></tbody></table></div><!--[if mso | IE]></td></tr></table><![endif]--></td></tr></tbody></table></div><!--[if mso | IE]></td></tr></table><table align=\"center\" border=\"0\" cellpadding=\"0\" cellspacing=\"0\" class=\"\" role=\"presentation\" style=\"width:600px;\" width=\"600\" bgcolor=\"#f4f4f5\" ><tr><td style=\"line-height:0px;font-size:0px;mso-line-height-rule:exactly;\"><![endif]--><div style=\"background:#f4f4f5;background-color:#f4f4f5;margin:0px auto;max-width:600px;\"><table align=\"center\" border=\"0\" cellpadding=\"0\" cellspacing=\"0\" role=\"presentation\" style=\"background:#f4f4f5;background-color:#f4f4f5;width:100%;\"><tbody><tr><td style=\"direction:ltr;font-size:0px;padding:0 16px 32px;text-align:center;\"><!--[if mso | IE]><table role=\"presentation\" border=\"0\" cellpadding=\"0\" cellspacing=\"0\"><tr><td class=\"\" width=\"600px\" ><table align=\"center\" border=\"0\" cellpadding=\"0\" cellspacing=\"0\" class=\"\" role=\"presentation\" style=\"width:568px;\" width=\"568\" bgcolor=\"#ffffff\" ><tr><td style=\"line-height:0px;font-size:0px;mso-line-height-rule:exactly;\"><![endif]--><div style=\"background:#ffffff;background-color:#ffffff;margin:0px auto;max-width:568px;border-radius:12px;overflow:hidden;\"><table align=\"center\" border=\"0\" cellpadding=\"0\" cellspacing=\"0\" role=\"presentation\" style=\"background:#ffffff;background-color:#ffffff;width:100%;border-collapse:separate;\"><tbody><tr><td style=\"border-radius:12px;direction:ltr;font-size:0px;padding:40px 32px 32px;text-align:center;\"><!--[if mso | IE]><table role=\"presentation\" border=\"0\" cellpadding=\"0\" cellspacing=\"0\"><tr><td class=\"\" style=\"vertical-align:top;width:504px;\" ><![endif]--><div class=\"mj-column-per-100 mj-outlook-group-fix\" style=\"font-size:0px;text-align:left;direction:ltr;display:inline-block;vertical-align:top;width:100%;\"><table border=\"0\" cellpadding=\"0\" cellspacing=\"0\" role=\"presentation\" style=\"vertical-align:top;\" width=\"100%\"><tbody><tr><td align=\"left\" style=\"font-size:0px;padding:10px 25px;padding-bottom:4px;word-break:break-word;\"><div style=\"font-family:system-ui, -apple-system, BlinkMacSystemFont, 'Segoe UI', Roboto, sans-serif;font-size:22px;font-weight:700;line-height:1.6;text-align:left;color:#18181b;\">New Applicant Interest</div></td></tr><tr><td align=\"left\" style=\"font-size:0px;padding:10px 25px;padding-bottom:24px;word-break:break-word;\"><div style=\"font-family:system-ui, -apple-system, BlinkMacSystemFont, 'Segoe UI', Roboto, sans-serif;font-size:14px;line-height:1.6;text-align:left;color:#71717a;\">A new candidate has expressed interest in WattsForWorkers.</div></td></tr><tr><td align=\"center\" style=\"font-size:0px;padding:0 0 24px;word-break:break-word;\"><p style=\"border-top:solid 1px #e4e4e7;font-size:1px;margin:0px auto;width:100%;\"></p><!--[if mso | IE]><table align=\"center\" border=\"0\" cellpadding=\"0\" cellspacing=\"0\" style=\"border-top:solid 1px #e4e4e7;font-size:1px;margin:0px auto;width:504px;\" role=\"presentation\" width=\"504px\" ><tr><td style=\"height:0;line-height:0;\"> &nbsp;</td></tr></table><![endif]--></td></tr></tbody></table></div><!--[if mso | IE]></td></tr></table><![endif]--></td></tr></tbody></table></div><!--[if mso | IE]></td></tr></table></td></tr><tr><td class=\"\" width=\"600px\" ><table align=\"center\" border=\"0\" cellpadding=\"0\" cellspacing=\"0\" class=\"\" role=\"presentation\" style=\"width:568px;\" width=\"568\" bgcolor=\"#ffffff\" ><tr><td style=\"line-height:0px;font-size:0px;mso-line-height-rule:exactly;\"><![endif]--><div style=\"background:#ffffff;background-color:#ffffff;margin:0px auto;max-width:568px;border-radius:12px;overflow:hidden;\"><table align=\"center\" border=\"0\" cellpadding=\"0\" cellspacing=\"0\" role=\"presentation\" style=\"background:#ffffff;background-color:#ffffff;width:100%;border-collapse:separate;\"><tbody><tr><td style=\"border-radius:12px;direction:ltr;font-size:0px;padding:0 32px 8px;text-align:center;\"><!--[if mso | IE]><table role=\"presentation\" border=\"0\" cellpadding=\"0\" cellspacing=\"0\"><tr><td class=\"\" style=\"vertical-align:top;width:504px;\" ><![endif]--><div class=\"mj-column-per-100 mj-outlook-group-fix\" style=\"font-size:0px;text-align:left;direction:ltr;display:inline-block;vertical-align:top;width:100%;\"><table border=\"0\" cellpadding=\"0\" cellspacing=\"0\" role=\"presentation\" width=\"100%\" style=\"border-collapse:separate;\"><tbody><tr><td style=\"background-color:#f4f4f5;border-radius:8px;vertical-align:top;border-collapse:separate;padding:20px;\"><table border=\"0\" cellpadding=\"0\" cellspacing=\"0\" role=\"presentation\" width=\"100%\"><tbody><tr><td align=\"left\" style=\"font-size:0px;padding:0 0 4px;word-break:break-word;\"><div style=\"font-family:system-ui, -apple-system, BlinkMacSystemFont, 'Segoe UI', Roboto, sans-serif;font-size:11px;line-height:1.6;text-align:left;color:#71717a;\">NAME</div></td></tr><tr><td align=\"left\" style=\"font-size:0px;padding:0;word-break:break-word;\"><div style=\"font-family:system-ui, -apple-system, BlinkMacSystemFont, 'Segoe UI', Roboto, sans-serif;font-size:16px;font-weight:600;line-height:1.6;text-align:left;color:#18181b;\">{{ $('Validate Input').item.json.data.first_name }} {{ $('Validate Input').item.json.data.last_name }}</div></td></tr></tbody></table></td></tr></tbody></table></div><!--[if mso | IE]></td></tr></table><![endif]--></td></tr></tbody></table></div><!--[if mso | IE]></td></tr></table></td></tr><tr><td class=\"\" width=\"600px\" ><table align=\"center\" border=\"0\" cellpadding=\"0\" cellspacing=\"0\" class=\"\" role=\"presentation\" style=\"width:568px;\" width=\"568\" bgcolor=\"#ffffff\" ><tr><td style=\"line-height:0px;font-size:0px;mso-line-height-rule:exactly;\"><![endif]--><div style=\"background:#ffffff;background-color:#ffffff;margin:0px auto;max-width:568px;border-radius:12px;overflow:hidden;\"><table align=\"center\" border=\"0\" cellpadding=\"0\" cellspacing=\"0\" role=\"presentation\" style=\"background:#ffffff;background-color:#ffffff;width:100%;border-collapse:separate;\"><tbody><tr><td style=\"border-radius:12px;direction:ltr;font-size:0px;padding:0 32px 8px;text-align:center;\"><!--[if mso | IE]><table role=\"presentation\" border=\"0\" cellpadding=\"0\" cellspacing=\"0\"><tr><td class=\"\" style=\"vertical-align:top;width:504px;\" ><![endif]--><div class=\"mj-column-per-100 mj-outlook-group-fix\" style=\"font-size:0px;text-align:left;direction:ltr;display:inline-block;vertical-align:top;width:100%;\"><table border=\"0\" cellpadding=\"0\" cellspacing=\"0\" role=\"presentation\" width=\"100%\" style=\"border-collapse:separate;\"><tbody><tr><td style=\"background-color:#f4f4f5;border-radius:8px;vertical-align:top;border-collapse:separate;padding:20px;\"><table border=\"0\" cellpadding=\"0\" cellspacing=\"0\" role=\"presentation\" width=\"100%\"><tbody><tr><td align=\"left\" style=\"font-size:0px;padding:0 0 4px;word-break:break-word;\"><div style=\"font-family:system-ui, -apple-system, BlinkMacSystemFont, 'Segoe UI', Roboto, sans-serif;font-size:11px;line-height:1.6;text-align:left;color:#71717a;\">EMAIL</div></td></tr><tr><td align=\"left\" style=\"font-size:0px;padding:0;word-break:break-word;\"><div style=\"font-family:system-ui, -apple-system, BlinkMacSystemFont, 'Segoe UI', Roboto, sans-serif;font-size:16px;font-weight:600;line-height:1.6;text-align:left;color:#18181b;\">{{ $('Validate Input').item.json.data.email }}</div></td></tr></tbody></table></td></tr></tbody></table></div><!--[if mso | IE]></td></tr></table><![endif]--></td></tr></tbody></table></div><!--[if mso | IE]></td></tr></table></td></tr><tr><td class=\"\" width=\"600px\" ><table align=\"center\" border=\"0\" cellpadding=\"0\" cellspacing=\"0\" class=\"\" role=\"presentation\" style=\"width:568px;\" width=\"568\" bgcolor=\"#ffffff\" ><tr><td style=\"line-height:0px;font-size:0px;mso-line-height-rule:exactly;\"><![endif]--><div style=\"background:#ffffff;background-color:#ffffff;margin:0px auto;max-width:568px;border-radius:12px;overflow:hidden;\"><table align=\"center\" border=\"0\" cellpadding=\"0\" cellspacing=\"0\" role=\"presentation\" style=\"background:#ffffff;background-color:#ffffff;width:100%;border-collapse:separate;\"><tbody><tr><td style=\"border-radius:12px;direction:ltr;font-size:0px;padding:0 32px 8px;text-align:center;\"><!--[if mso | IE]><table role=\"presentation\" border=\"0\" cellpadding=\"0\" cellspacing=\"0\"><tr><td class=\"\" style=\"vertical-align:top;width:504px;\" ><![endif]--><div class=\"mj-column-per-100 mj-outlook-group-fix\" style=\"font-size:0px;text-align:left;direction:ltr;display:inline-block;vertical-align:top;width:100%;\"><table border=\"0\" cellpadding=\"0\" cellspacing=\"0\" role=\"presentation\" width=\"100%\" style=\"border-collapse:separate;\"><tbody><tr><td style=\"background-color:#f4f4f5;border-radius:8px;vertical-align:top;border-collapse:separate;padding:20px;\"><table border=\"0\" cellpadding=\"0\" cellspacing=\"0\" role=\"presentation\" width=\"100%\"><tbody><tr><td align=\"left\" style=\"font-size:0px;padding:0 0 4px;word-break:break-word;\"><div style=\"font-family:system-ui, -apple-system, BlinkMacSystemFont, 'Segoe UI', Roboto, sans-serif;font-size:11px;line-height:1.6;text-align:left;color:#71717a;\">PHONE</div></td></tr><tr><td align=\"left\" style=\"font-size:0px;padding:0;word-break:break-word;\"><div style=\"font-family:system-ui, -apple-system, BlinkMacSystemFont, 'Segoe UI', Roboto, sans-serif;font-size:16px;font-weight:600;line-height:1.6;text-align:left;color:#18181b;\">{{ $('Validate Input').item.json.data.phone }}</div></td></tr></tbody></table></td></tr></tbody></table></div><!--[if mso | IE]></td></tr></table><![endif]--></td></tr></tbody></table></div><!--[if mso | IE]></td></tr></table></td></tr><tr><td class=\"\" width=\"600px\" ><table align=\"center\" border=\"0\" cellpadding=\"0\" cellspacing=\"0\" class=\"\" role=\"presentation\" style=\"width:568px;\" width=\"568\" bgcolor=\"#ffffff\" ><tr><td style=\"line-height:0px;font-size:0px;mso-line-height-rule:exactly;\"><![endif]--><div style=\"background:#ffffff;background-color:#ffffff;margin:0px auto;max-width:568px;border-radius:12px;overflow:hidden;\"><table align=\"center\" border=\"0\" cellpadding=\"0\" cellspacing=\"0\" role=\"presentation\" style=\"background:#ffffff;background-color:#ffffff;width:100%;border-collapse:separate;\"><tbody><tr><td style=\"border-radius:12px;direction:ltr;font-size:0px;padding:0 32px 8px;text-align:center;\"><!--[if mso | IE]><table role=\"presentation\" border=\"0\" cellpadding=\"0\" cellspacing=\"0\"><tr><td class=\"\" style=\"vertical-align:top;width:504px;\" ><![endif]--><div class=\"mj-column-per-100 mj-outlook-group-fix\" style=\"font-size:0px;text-align:left;direction:ltr;display:inline-block;vertical-align:top;width:100%;\"><table border=\"0\" cellpadding=\"0\" cellspacing=\"0\" role=\"presentation\" width=\"100%\" style=\"border-collapse:separate;\"><tbody><tr><td style=\"background-color:#f4f4f5;border-radius:8px;vertical-align:top;border-collapse:separate;padding:20px;\"><table border=\"0\" cellpadding=\"0\" cellspacing=\"0\" role=\"presentation\" width=\"100%\"><tbody><tr><td align=\"left\" style=\"font-size:0px;padding:0 0 4px;word-break:break-word;\"><div style=\"font-family:system-ui, -apple-system, BlinkMacSystemFont, 'Segoe UI', Roboto, sans-serif;font-size:11px;line-height:1.6;text-align:left;color:#71717a;\">ROLE INTEREST</div></td></tr><tr><td align=\"left\" style=\"font-size:0px;padding:0;word-break:break-word;\"><div style=\"font-family:system-ui, -apple-system, BlinkMacSystemFont, 'Segoe UI', Roboto, sans-serif;font-size:16px;font-weight:600;line-height:1.6;text-align:left;color:#18181b;\">{{ $('Validate Input').item.json.data.role_interest }}</div></td></tr></tbody></table></td></tr></tbody></table></div><!--[if mso | IE]></td></tr></table><![endif]--></td></tr></tbody></table></div><!--[if mso | IE]></td></tr></table></td></tr><tr><td class=\"\" width=\"600px\" ><table align=\"center\" border=\"0\" cellpadding=\"0\" cellspacing=\"0\" class=\"\" role=\"presentation\" style=\"width:568px;\" width=\"568\" bgcolor=\"#ffffff\" ><tr><td style=\"line-height:0px;font-size:0px;mso-line-height-rule:exactly;\"><![endif]--><div style=\"background:#ffffff;background-color:#ffffff;margin:0px auto;max-width:568px;border-radius:12px;overflow:hidden;\"><table align=\"center\" border=\"0\" cellpadding=\"0\" cellspacing=\"0\" role=\"presentation\" style=\"background:#ffffff;background-color:#ffffff;width:100%;border-collapse:separate;\"><tbody><tr><td style=\"border-radius:12px;direction:ltr;font-size:0px;padding:0 32px 32px;text-align:center;\"><!--[if mso | IE]><table role=\"presentation\" border=\"0\" cellpadding=\"0\" cellspacing=\"0\"><tr><td class=\"\" style=\"vertical-align:top;width:504px;\" ><![endif]--><div class=\"mj-column-per-100 mj-outlook-group-fix\" style=\"font-size:0px;text-align:left;direction:ltr;display:inline-block;vertical-align:top;width:100%;\"><table border=\"0\" cellpadding=\"0\" cellspacing=\"0\" role=\"presentation\" width=\"100%\" style=\"border-collapse:separate;\"><tbody><tr><td style=\"background-color:#f4f4f5;border-radius:8px;vertical-align:top;border-collapse:separate;padding:20px;\"><table border=\"0\" cellpadding=\"0\" cellspacing=\"0\" role=\"presentation\" width=\"100%\"><tbody><tr><td align=\"left\" style=\"font-size:0px;padding:0 0 4px;word-break:break-word;\"><div style=\"font-family:system-ui, -apple-system, BlinkMacSystemFont, 'Segoe UI', Roboto, sans-serif;font-size:11px;line-height:1.6;text-align:left;color:#71717a;\">MESSAGE</div></td></tr><tr><td align=\"left\" style=\"font-size:0px;padding:0;word-break:break-word;\"><div style=\"font-family:system-ui, -apple-system, BlinkMacSystemFont, 'Segoe UI', Roboto, sans-serif;font-size:16px;font-weight:600;line-height:1.6;text-align:left;color:#18181b;\">{{ $('Validate Input').item.json.data.message }}</div></td></tr></tbody></table></td></tr></tbody></table></div><!--[if mso | IE]></td></tr></table><![endif]--></td></tr></tbody></table></div><!--[if mso | IE]></td></tr></table></td></tr><tr><td class=\"\" width=\"600px\" ><table align=\"center\" border=\"0\" cellpadding=\"0\" cellspacing=\"0\" class=\"\" role=\"presentation\" style=\"width:568px;\" width=\"568\" ><tr><td style=\"line-height:0px;font-size:0px;mso-line-height-rule:exactly;\"><![endif]--><div style=\"margin:0px auto;max-width:568px;\"><table align=\"center\" border=\"0\" cellpadding=\"0\" cellspacing=\"0\" role=\"presentation\" style=\"width:100%;\"><tbody><tr><td style=\"direction:ltr;font-size:0px;padding:24px 32px 0;text-align:center;\"><!--[if mso | IE]><table role=\"presentation\" border=\"0\" cellpadding=\"0\" cellspacing=\"0\"><tr><td class=\"\" style=\"vertical-align:top;width:504px;\" ><![endif]--><div class=\"mj-column-per-100 mj-outlook-group-fix\" style=\"font-size:0px;text-align:left;direction:ltr;display:inline-block;vertical-align:top;width:100%;\"><table border=\"0\" cellpadding=\"0\" cellspacing=\"0\" role=\"presentation\" style=\"vertical-align:top;\" width=\"100%\"><tbody><tr><td align=\"center\" style=\"font-size:0px;padding:10px 25px;word-break:break-word;\"><div style=\"font-family:system-ui, -apple-system, BlinkMacSystemFont, 'Segoe UI', Roboto, sans-serif;font-size:12px;line-height:1.6;text-align:center;color:#a1a1aa;\">ThisWay Global &middot; Austin, TX</div></td></tr></tbody></table></div><!--[if mso | IE]></td></tr></table><![endif]--></td></tr></tbody></table></div><!--[if mso | IE]></td></tr></table></td></tr></table><![endif]--></td></tr></tbody></table></div><!--[if mso | IE]></td></tr></table><![endif]--></div></body></html>"
      },
      "type": "n8n-nodes-base.mailgun",
      "typeVersion": 1,
      "position": [
        928,
        1300
      ],
      "id": "a1b2c3d4-0001-0001-0001-000000000013",
      "name": "W4W: Notify Admin",
      "credentials": {
        "mailgunApi": {
          "id": "lHQnhWsSULcKXB4f",
          "name": "Amalgamy.ai"
        }
      }
    },
    {
      "parameters": {
        "fromEmail": "notifications@m.thiswayglobal.com",
        "toEmail": "={{ $('Validate Input').item.json.data.email }}",
        "subject": "=Thank You for Your Interest",
        "html": "=<!doctype html><html lang=\"und\" dir=\"auto\" xmlns=\"http://www.w3.org/1999/xhtml\" xmlns:v=\"urn:schemas-microsoft-com:vml\" xmlns:o=\"urn:schemas-microsoft-com:office:office\"><head><title></title><!--[if !mso]><!--><meta http-equiv=\"X-UA-Compatible\" content=\"IE=edge\"><!--<![endif]--><meta http-equiv=\"Content-Type\" content=\"text/html; charset=UTF-8\"><meta name=\"viewport\" content=\"width=device-width,initial-scale=1\"><style type=\"text/css\">#outlook a {      padding: 0;    }    body {      margin: 0;      padding: 0;      -webkit-text-size-adjust: 100%;      -ms-text-size-adjust: 100%;    }    table,    td {      border-collapse: collapse;      mso-table-lspace: 0pt;      mso-table-rspace: 0pt;    }    img {      border: 0;      height: auto;      line-height: 100%;      outline: none;      text-decoration: none;      -ms-interpolation-mode: bicubic;    }    p {      display: block;      margin: 13px 0;    }</style><!--[if mso]>    <noscript>    <xml>    <o:OfficeDocumentSettings>      <o:AllowPNG/>      <o:PixelsPerInch>96</o:PixelsPerInch>    </o:OfficeDocumentSettings>    </xml>    </noscript>    <![endif]--><!--[if lte mso 11]>    <style type=\"text/css\">      .mj-outlook-group-fix { width:100% !important; }    </style>    <![endif]--><!--[if !mso]><!--><link href=\"https://fonts.googleapis.com/css?family=Roboto:300,400,500,700\" rel=\"stylesheet\" type=\"text/css\"><style type=\"text/css\">@import url(https://fonts.googleapis.com/css?family=Roboto:300,400,500,700);</style><!--<![endif]--><style type=\"text/css\">@media only screen and (min-width:480px) {      .mj-column-per-100 {        width: 100% !important;        max-width: 100%;      }    }</style><style media=\"screen and (min-width:480px)\">.moz-text-html .mj-column-per-100 {      width: 100% !important;      max-width: 100%;    }</style><style type=\"text/css\">@media only screen and (max-width:479px) {      table.mj-full-width-mobile {        width: 100% !important;      }      td.mj-full-width-mobile {        width: auto !important;      }    }</style></head><body style=\"word-spacing:normal;background-color:#f4f4f5;\"><div aria-roledescription=\"email\" style=\"background-color:#f4f4f5;\" role=\"article\" lang=\"und\" dir=\"auto\"><!--[if mso | IE]><table align=\"center\" border=\"0\" cellpadding=\"0\" cellspacing=\"0\" class=\"\" role=\"presentation\" style=\"width:600px;\" width=\"600\" ><tr><td style=\"line-height:0px;font-size:0px;mso-line-height-rule:exactly;\"><![endif]--><div style=\"margin:0px auto;max-width:600px;\"><table align=\"center\" border=\"0\" cellpadding=\"0\" cellspacing=\"0\" role=\"presentation\" style=\"width:100%;\"><tbody><tr><td style=\"direction:ltr;font-size:0px;padding:32px 16px 0;text-align:center;\"><!--[if mso | IE]><table role=\"presentation\" border=\"0\" cellpadding=\"0\" cellspacing=\"0\"><tr><td class=\"\" style=\"vertical-align:top;width:568px;\" ><![endif]--><div class=\"mj-column-per-100 mj-outlook-group-fix\" style=\"font-size:0px;text-align:left;direction:ltr;display:inline-block;vertical-align:top;width:100%;\"><table border=\"0\" cellpadding=\"0\" cellspacing=\"0\" role=\"presentation\" style=\"vertical-align:top;\" width=\"100%\"><tbody><tr><td align=\"center\" style=\"font-size:0px;padding:10px 25px;padding-bottom:24px;word-break:break-word;\"><table border=\"0\" cellpadding=\"0\" cellspacing=\"0\" role=\"presentation\" style=\"border-collapse:collapse;border-spacing:0px;\"><tbody><tr><td style=\"width:140px;\"><img alt=\"ThisWay Global\" src=\"https://thiswayglobal.com/images/logo.png\" style=\"border:0;display:block;outline:none;text-decoration:none;height:auto;width:100%;font-size:13px;\" width=\"140\" height=\"auto\"></td></tr></tbody></table></td></tr></tbody></table></div><!--[if mso | IE]></td></tr></table><![endif]--></td></tr></tbody></table></div><!--[if mso | IE]></td></tr></table><table align=\"center\" border=\"0\" cellpadding=\"0\" cellspacing=\"0\" class=\"\" role=\"presentation\" style=\"width:600px;\" width=\"600\" bgcolor=\"#f4f4f5\" ><tr><td style=\"line-height:0px;font-size:0px;mso-line-height-rule:exactly;\"><![endif]--><div style=\"background:#f4f4f5;background-color:#f4f4f5;margin:0px auto;max-width:600px;\"><table align=\"center\" border=\"0\" cellpadding=\"0\" cellspacing=\"0\" role=\"presentation\" style=\"background:#f4f4f5;background-color:#f4f4f5;width:100%;\"><tbody><tr><td style=\"direction:ltr;font-size:0px;padding:0 16px 32px;text-align:center;\"><!--[if mso | IE]><table role=\"presentation\" border=\"0\" cellpadding=\"0\" cellspacing=\"0\"><tr><td class=\"\" width=\"600px\" ><table align=\"center\" border=\"0\" cellpadding=\"0\" cellspacing=\"0\" class=\"\" role=\"presentation\" style=\"width:568px;\" width=\"568\" bgcolor=\"#ffffff\" ><tr><td style=\"line-height:0px;font-size:0px;mso-line-height-rule:exactly;\"><![endif]--><div style=\"background:#ffffff;background-color:#ffffff;margin:0px auto;max-width:568px;border-radius:12px;overflow:hidden;\"><table align=\"center\" border=\"0\" cellpadding=\"0\" cellspacing=\"0\" role=\"presentation\" style=\"background:#ffffff;background-color:#ffffff;width:100%;border-collapse:separate;\"><tbody><tr><td style=\"border-radius:12px;direction:ltr;font-size:0px;padding:40px 32px 32px;text-align:center;\"><!--[if mso | IE]><table role=\"presentation\" border=\"0\" cellpadding=\"0\" cellspacing=\"0\"><tr><td class=\"\" style=\"vertical-align:top;width:504px;\" ><![endif]--><div class=\"mj-column-per-100 mj-outlook-group-fix\" style=\"font-size:0px;text-align:left;direction:ltr;display:inline-block;vertical-align:top;width:100%;\"><table border=\"0\" cellpadding=\"0\" cellspacing=\"0\" role=\"presentation\" style=\"vertical-align:top;\" width=\"100%\"><tbody><tr><td align=\"left\" style=\"font-size:0px;padding:10px 25px;padding-bottom:4px;word-break:break-word;\"><div style=\"font-family:system-ui, -apple-system, BlinkMacSystemFont, 'Segoe UI', Roboto, sans-serif;font-size:22px;font-weight:700;line-height:1.6;text-align:left;color:#18181b;\">Interest Received</div></td></tr><tr><td align=\"left\" style=\"font-size:0px;padding:10px 25px;padding-bottom:24px;word-break:break-word;\"><div style=\"font-family:system-ui, -apple-system, BlinkMacSystemFont, 'Segoe UI', Roboto, sans-serif;font-size:14px;line-height:1.6;text-align:left;color:#71717a;\">Thank you for your interest in WattsForWorkers.</div></td></tr><tr><td align=\"center\" style=\"font-size:0px;padding:0 0 24px;word-break:break-word;\"><p style=\"border-top:solid 1px #e4e4e7;font-size:1px;margin:0px auto;width:100%;\"></p><!--[if mso | IE]><table align=\"center\" border=\"0\" cellpadding=\"0\" cellspacing=\"0\" style=\"border-top:solid 1px #e4e4e7;font-size:1px;margin:0px auto;width:504px;\" role=\"presentation\" width=\"504px\" ><tr><td style=\"height:0;line-height:0;\"> &nbsp;</td></tr></table><![endif]--></td></tr><tr><td align=\"left\" style=\"font-size:0px;padding:10px 25px;padding-bottom:16px;word-break:break-word;\"><div style=\"font-family:system-ui, -apple-system, BlinkMacSystemFont, 'Segoe UI', Roboto, sans-serif;font-size:15px;line-height:1.6;text-align:left;color:#18181b;\">Hi {{ $('Validate Input').item.json.data.first_name }},</div></td></tr><tr><td align=\"left\" style=\"font-size:0px;padding:10px 25px;padding-bottom:16px;word-break:break-word;\"><div style=\"font-family:system-ui, -apple-system, BlinkMacSystemFont, 'Segoe UI', Roboto, sans-serif;font-size:15px;line-height:1.6;text-align:left;color:#18181b;\">Thank you for expressing your interest in the WattsForWorkers program. We've received your submission and our team will follow up with you soon to discuss next steps and opportunities.</div></td></tr></tbody></table></div><!--[if mso | IE]></td></tr></table><![endif]--></td></tr></tbody></table></div><!--[if mso | IE]></td></tr></table></td></tr><tr><td class=\"\" width=\"600px\" ><table align=\"center\" border=\"0\" cellpadding=\"0\" cellspacing=\"0\" class=\"\" role=\"presentation\" style=\"width:568px;\" width=\"568\" bgcolor=\"#ffffff\" ><tr><td style=\"line-height:0px;font-size:0px;mso-line-height-rule:exactly;\"><![endif]--><div style=\"background:#ffffff;background-color:#ffffff;margin:0px auto;max-width:568px;border-radius:12px;overflow:hidden;\"><table align=\"center\" border=\"0\" cellpadding=\"0\" cellspacing=\"0\" role=\"presentation\" style=\"background:#ffffff;background-color:#ffffff;width:100%;border-collapse:separate;\"><tbody><tr><td style=\"border-radius:12px;direction:ltr;font-size:0px;padding:0 32px 24px;text-align:center;\"><!--[if mso | IE]><table role=\"presentation\" border=\"0\" cellpadding=\"0\" cellspacing=\"0\"><tr><td class=\"\" style=\"vertical-align:top;width:504px;\" ><![endif]--><div class=\"mj-column-per-100 mj-outlook-group-fix\" style=\"font-size:0px;text-align:left;direction:ltr;display:inline-block;vertical-align:top;width:100%;\"><table border=\"0\" cellpadding=\"0\" cellspacing=\"0\" role=\"presentation\" width=\"100%\" style=\"border-collapse:separate;\"><tbody><tr><td style=\"background-color:#f4f4f5;border-radius:8px;vertical-align:top;border-collapse:separate;padding:20px;\"><table border=\"0\" cellpadding=\"0\" cellspacing=\"0\" role=\"presentation\" width=\"100%\"><tbody><tr><td align=\"left\" style=\"font-size:0px;padding:0 0 4px;word-break:break-word;\"><div style=\"font-family:system-ui, -apple-system, BlinkMacSystemFont, 'Segoe UI', Roboto, sans-serif;font-size:11px;line-height:1.6;text-align:left;color:#71717a;\">ROLE INTEREST</div></td></tr><tr><td align=\"left\" style=\"font-size:0px;padding:0;word-break:break-word;\"><div style=\"font-family:system-ui, -apple-system, BlinkMacSystemFont, 'Segoe UI', Roboto, sans-serif;font-size:16px;font-weight:600;line-height:1.6;text-align:left;color:#18181b;\">{{ $('Validate Input').item.json.data.role_interest }}</div></td></tr></tbody></table></td></tr></tbody></table></div><!--[if mso | IE]></td></tr></table><![endif]--></td></tr></tbody></table></div><!--[if mso | IE]></td></tr></table></td></tr><tr><td class=\"\" width=\"600px\" ><table align=\"center\" border=\"0\" cellpadding=\"0\" cellspacing=\"0\" class=\"\" role=\"presentation\" style=\"width:568px;\" width=\"568\" bgcolor=\"#ffffff\" ><tr><td style=\"line-height:0px;font-size:0px;mso-line-height-rule:exactly;\"><![endif]--><div style=\"background:#ffffff;background-color:#ffffff;margin:0px auto;max-width:568px;border-radius:12px;overflow:hidden;\"><table align=\"center\" border=\"0\" cellpadding=\"0\" cellspacing=\"0\" role=\"presentation\" style=\"background:#ffffff;background-color:#ffffff;width:100%;border-collapse:separate;\"><tbody><tr><td style=\"border-radius:12px;direction:ltr;font-size:0px;padding:0 32px 32px;text-align:center;\"><!--[if mso | IE]><table role=\"presentation\" border=\"0\" cellpadding=\"0\" cellspacing=\"0\"><tr><td class=\"\" style=\"vertical-align:top;width:504px;\" ><![endif]--><div class=\"mj-column-per-100 mj-outlook-group-fix\" style=\"font-size:0px;text-align:left;direction:ltr;display:inline-block;vertical-align:top;width:100%;\"><table border=\"0\" cellpadding=\"0\" cellspacing=\"0\" role=\"presentation\" style=\"vertical-align:top;\" width=\"100%\"><tbody><tr><td align=\"left\" style=\"font-size:0px;padding:10px 25px;padding-top:8px;word-break:break-word;\"><div style=\"font-family:system-ui, -apple-system, BlinkMacSystemFont, 'Segoe UI', Roboto, sans-serif;font-size:15px;line-height:1.6;text-align:left;color:#18181b;\">Best regards,<br><strong>The ThisWay Global Team</strong></div></td></tr></tbody></table></div><!--[if mso | IE]></td></tr></table><![endif]--></td></tr></tbody></table></div><!--[if mso | IE]></td></tr></table></td></tr><tr><td class=\"\" width=\"600px\" ><table align=\"center\" border=\"0\" cellpadding=\"0\" cellspacing=\"0\" class=\"\" role=\"presentation\" style=\"width:568px;\" width=\"568\" ><tr><td style=\"line-height:0px;font-size:0px;mso-line-height-rule:exactly;\"><![endif]--><div style=\"margin:0px auto;max-width:568px;\"><table align=\"center\" border=\"0\" cellpadding=\"0\" cellspacing=\"0\" role=\"presentation\" style=\"width:100%;\"><tbody><tr><td style=\"direction:ltr;font-size:0px;padding:24px 32px 0;text-align:center;\"><!--[if mso | IE]><table role=\"presentation\" border=\"0\" cellpadding=\"0\" cellspacing=\"0\"><tr><td class=\"\" style=\"vertical-align:top;width:504px;\" ><![endif]--><div class=\"mj-column-per-100 mj-outlook-group-fix\" style=\"font-size:0px;text-align:left;direction:ltr;display:inline-block;vertical-align:top;width:100%;\"><table border=\"0\" cellpadding=\"0\" cellspacing=\"0\" role=\"presentation\" style=\"vertical-align:top;\" width=\"100%\"><tbody><tr><td align=\"center\" style=\"font-size:0px;padding:10px 25px;word-break:break-word;\"><div style=\"font-family:system-ui, -apple-system, BlinkMacSystemFont, 'Segoe UI', Roboto, sans-serif;font-size:12px;line-height:1.6;text-align:center;color:#a1a1aa;\">ThisWay Global &middot; Austin, TX</div></td></tr></tbody></table></div><!--[if mso | IE]></td></tr></table><![endif]--></td></tr></tbody></table></div><!--[if mso | IE]></td></tr></table></td></tr></table><![endif]--></td></tr></tbody></table></div><!--[if mso | IE]></td></tr></table><![endif]--></div></body></html>"
      },
      "type": "n8n-nodes-base.mailgun",
      "typeVersion": 1,
      "position": [
        928,
        1400
      ],
      "id": "a1b2c3d4-0001-0001-0001-000000000014",
      "name": "W4W: Confirm User",
      "credentials": {
        "mailgunApi": {
          "id": "lHQnhWsSULcKXB4f",
          "name": "Amalgamy.ai"
        }
      }
    }
  ],
  "connections": {
    "Webhook": {
      "main": [
        [
          {
            "node": "Validate Input",
            "type": "main",
            "index": 0
          }
        ]
      ]
    },
    "Validate Input": {
      "main": [
        [
          {
            "node": "Route",
            "type": "main",
            "index": 0
          }
        ]
      ]
    },
    "Route": {
      "main": [
        [
          {
            "node": "Insert Submission",
            "type": "main",
            "index": 0
          }
        ],
        [
          {
            "node": "Error Response",
            "type": "main",
            "index": 0
          }
        ]
      ]
    },
    "Insert Submission": {
      "main": [
        [
          {
            "node": "Success Response",
            "type": "main",
            "index": 0
          },
          {
            "node": "Switch on Form Type",
            "type": "main",
            "index": 0
          }
        ]
      ]
    },
    "Switch on Form Type": {
      "main": [
        [
          {
            "node": "TTC: Notify Admin",
            "type": "main",
            "index": 0
          },
          {
            "node": "TTC: Confirm User",
            "type": "main",
            "index": 0
          }
        ],
        [
          {
            "node": "W4W: Notify Admin",
            "type": "main",
            "index": 0
          },
          {
            "node": "W4W: Confirm User",
            "type": "main",
            "index": 0
          }
        ]
      ]
    }
  },
  "pinData": {}
}